ircrobots/__init__.py
ircrobots/asyncs.py
ircrobots/bot.py
ircrobots/contexts.py
ircrobots/formatting.py
ircrobots/glob.py
ircrobots/interface.py
ircrobots/ircv3.py
ircrobots/params.py
ircrobots/py.typed
ircrobots/sasl.py
ircrobots/scram.py
ircrobots/security.py
ircrobots/server.py
ircrobots/struct.py
ircrobots/transport.py
ircrobots/matching/__init__.py
ircrobots/matching/params.py
ircrobots/matching/responses.py
ircrobots-0.7.2.dist-info/LICENSE
ircrobots-0.7.2.dist-info/METADATA
ircrobots-0.7.2.dist-info/WHEEL
ircrobots-0.7.2.dist-info/top_level.txt
ircrobots-0.7.2.dist-info/RECORD
