Metadata-Version: 2.1
Name: ircrobots
Version: 0.7.2
Summary: Asyncio IRC bot framework
Home-page: https://github.com/jesopo/ircrobots
Author: jesopo
Author-email: pip@jesopo.uk
Classifier: Programming Language :: Python :: 3
Classifier: License :: OSI Approved :: MIT License
Classifier: Operating System :: OS Independent
Classifier: Operating System :: POSIX
Classifier: Operating System :: Microsoft :: Windows
Classifier: Topic :: Communications :: Chat :: Internet Relay Chat
Requires-Python: >=3.7
License-File: LICENSE
Requires-Dist: anyio (~=2.0.2)
Requires-Dist: async-stagger (~=0.3.0)
Requires-Dist: async-timeout (~=4.0.2)
Requires-Dist: asyncio-rlock (~=0.1.0)
Requires-Dist: asyncio-throttle (~=1.0.1)
Requires-Dist: ircstates (~=0.13.0)
